[
    {
        "id": 1001,
        "type": "premium",
        "name": "Hiago Gabriel",
        "projectName": "WebWizard",
        "projectCategory": "Informativo",
        "counterName": "hiagogabriel",
        "instagramUrl": "www.instagram.com/hiago.gabriel.940098/",
        "githubUrl": "https://github.com/hiagogabrielga",
        "projectUrl": "https://hiagogabrielga.github.io/Front-end/Projeto-linguagens/",
        "imageSource": "1001"
    },
    {
        "id": 1002,
        "type": "gold",
        "name": "Vitor Cappeleto",
        "projectName": "Aurora",
        "projectCategory": "Tecnologia",
        "counterName": "vitorcappeleto",
        "instagramUrl": "https://www.instagram.com/capelleto_/",
        "githubUrl": "https://github.com/cappeLindo",
        "projectUrl": "https://cappelindo.github.io/frontend/aurora/",
        "imageSource": "1002"
    },
    {
        "id": 1003,
        "type": "gold",
        "name": "João Corso",
        "projectName": "CK Review",
        "projectCategory": "Review",
        "counterName": "joaocorso",
        "instagramUrl": "https://www.instagram.com/joao.corso.54/",
        "githubUrl": "https://github.com/Corso330Z",
        "projectUrl": "https://corso330z.github.io/site_mobile/",
        "imageSource": "1003"
    },
    {
        "id": 1004,
        "type": "normal",
        "name": "Alini de Sousa",
        "projectName": "América do Sul",
        "projectCategory": "Mapas",
        "counterName": "alinidesousa",
        "instagramUrl": "",
        "githubUrl": "https://github.com/alinisp",
        "projectUrl": "https://alinisp.github.io/Projeto_2/index.html",
        "imageSource": "default"
    },
    {
        "id": 1005,
        "type": "normal",
        "name": "Ana Caroline",
        "projectName": "Aroma and Cia",
        "projectCategory": "Viagens",
        "counterName": "anacaroline",
        "instagramUrl": "",
        "githubUrl": "https://github.com/anacaroline16",
        "projectUrl": "https://anacaroline16.github.io/Front_end_1/projeto_2/",
        "imageSource": "1005"
    },
    {
        "id": 1006,
        "type": "normal",
        "name": "Ana Isabely",
        "projectName": "Belck Closet",
        "projectCategory": "Roupas",
        "counterName": "anaisabely",
        "instagramUrl": "",
        "githubUrl": "https://github.com/belchiorisa",
        "projectUrl": "https://belchiorisa.github.io/Projeto2/",
        "imageSource": "1006"
    },
    {
        "id": 1007,
        "type": "normal",
        "name": "Anne Gabriele",
        "projectName": "Geração Fitness",
        "projectCategory": "Academia",
        "counterName": "annegabriele",
        "instagramUrl": "",
        "githubUrl": "https://github.com/annegabrielebassi",
        "projectUrl": "https://annegabrielebassi.github.io/",
        "imageSource": "default"
    },
    {
        "id": 1008,
        "type": "normal",
        "name": "Beatriz Eduarda",
        "projectName": "GRB",
        "projectCategory": "Ginástica",
        "counterName": "beatrizeduarda",
        "instagramUrl": "",
        "githubUrl": "https://github.com/beatriztesser",
        "projectUrl": "https://beatriztesser.github.io/Site/",
        "imageSource": "default"
    },
    {
        "id": 1010,
        "type": "normal",
        "name": "Carlos Eduardo",
        "projectName": "Avirt",
        "projectCategory": "Filmes",
        "counterName": "carloseduardo",
        "instagramUrl": "",
        "githubUrl": "https://github.com/carlinlambimia",
        "projectUrl": "https://carlinlambimia.github.io/CarlinLambiMia1/",
        "imageSource": "default"
    },
    {
        "id": 1011,
        "type": "normal",
        "name": "Isabelly Lopes",
        "projectName": "Blog de Análises",
        "projectCategory": "Esportes",
        "counterName": "isabellylopes",
        "instagramUrl": "",
        "githubUrl": "https://github.com/isabellylinda",
        "projectUrl": "https://isabellylinda.github.io/site/projeto.02/",
        "imageSource": "default"
    },
    {
        "id": 1012,
        "type": "normal",
        "name": "João Inglez",
        "projectName": "Coffee Hut",
        "projectCategory": "Cafeteria",
        "counterName": "joaoinglez",
        "instagramUrl": "",
        "githubUrl": "https://github.com/JoaoInglez387",
        "projectUrl": "",
        "imageSource": "1012"
    },
    {
        "id": 1013,
        "type": "normal",
        "name": "João Andrade",
        "projectName": "Cortes de Cabelo",
        "projectCategory": "Estética",
        "counterName": "joaoandrade",
        "instagramUrl": "",
        "githubUrl": "https://github.com/joaobent",
        "projectUrl": "https://joaobent.github.io/Front_end/Meu%20site/index.html",
        "imageSource": "default"
    },
    {
        "id": 1014,
        "type": "normal",
        "name": "João Guerini",
        "projectName": "WaterPods",
        "projectCategory": "Tecnologia",
        "counterName": "joaoguerini",
        "instagramUrl": "https://www.instagram.com/joaopedrogp01/",
        "githubUrl": "https://github.com/JoaoInglez387",
        "projectUrl": "https://joaoguerini.github.io/AulaIFRO/front-end/projeto/index.html",
        "imageSource": "1014"
    },
    {
        "id": 1015,
        "type": "normal",
        "name": "João Lopes",
        "projectName": "LP Components",
        "projectCategory": "Tecnologia",
        "counterName": "joaolopes",
        "instagramUrl": "",
        "githubUrl": "https://github.com/lopes-vh",
        "projectUrl": "https://lopes-vh.github.io/componentes/",
        "imageSource": "1015"
    },
    {
        "id": 1017,
        "type": "normal",
        "name": "Júlia de Abreu",
        "projectName": "Marília Mendonça",
        "projectCategory": "Personalidade",
        "counterName": "juliaabreu",
        "instagramUrl": "",
        "githubUrl": "https://github.com/juliadeabre0",
        "projectUrl": "https://juliadeabre0.github.io/projeto-livre/",
        "imageSource": "default"
    },
    {
        "id": 1018,
        "type": "normal",
        "name": "Júlia Pereira",
        "projectName": "Cinecia",
        "projectCategory": "Filmes",
        "counterName": "juliapereira",
        "instagramUrl": "",
        "githubUrl": "https://github.com/julpereira",
        "projectUrl": "https://julpereira.github.io/julpereira.github/diret%C3%B3rio-raiz/site-sala-aula/index.html",
        "imageSource": "default"
    },
    {
        "id": 1019,
        "type": "normal",
        "name": "Lavínia Stein",
        "projectName": "Cooking",
        "projectCategory": "Receitas",
        "counterName": "laviniastein",
        "instagramUrl": "",
        "githubUrl": "https://github.com/steinlavinia",
        "projectUrl": "https://steinlavinia.github.io/projeto2/siteCooking/index.html",
        "imageSource": "default"
    },
    {
        "id": 1020,
        "type": "normal",
        "name": "Letícia Silva",
        "projectName": "Amor de 4 patas",
        "projectCategory": "Natureza",
        "counterName": "laticiasilva",
        "instagramUrl": "",
        "githubUrl": "https://github.com/leticiad3br27",
        "projectUrl": "https://leticiad3br27.github.io/meusite/",
        "imageSource": "default"
    },
    {
        "id": 1021,
        "type": "normal",
        "name": "Lívia Darold",
        "projectName": "Receitas",
        "projectCategory": "Receitas",
        "counterName": "laviniastein",
        "instagramUrl": "",
        "githubUrl": "https://github.com/darold08",
        "projectUrl": "https://darold08.github.io/projeto_mobile/html/index.html",
        "imageSource": "default"
    },
    {
        "id": 1022,
        "type": "normal",
        "name": "Luana Vitória",
        "projectName": "América do Sul",
        "projectCategory": "Mapas",
        "counterName": "luanavitoria",
        "instagramUrl": "",
        "githubUrl": "https://github.com/luanavitori",
        "projectUrl": "https://luanavitori.github.io/projeto%202/index.html",
        "imageSource": "default"
    },
    {
        "id": 1023,
        "type": "normal",
        "name": "Luz Miranda",
        "projectName": "Vegan",
        "projectCategory": "Receitas",
        "counterName": "luzmiranda",
        "instagramUrl": "",
        "githubUrl": "https://github.com/luzzzmiranda",
        "projectUrl": "https://luzzzmiranda.github.io/frontend_2bimestre/culinariaVegana/",
        "imageSource": "default"
    },
    {
        "id": 1025,
        "type": "normal",
        "name": "Maria Oliveira",
        "projectName": "Bate-Papo-Alimentar",
        "projectCategory": "Receitas",
        "counterName": "mariaoliveira",
        "instagramUrl": "",
        "githubUrl": "https://github.com/oliveiraduda123",
        "projectUrl": "",
        "imageSource": "default"
    },
    {
        "id": 1026,
        "type": "normal",
        "name": "Maria Golçalves",
        "projectName": "BMD",
        "projectCategory": "Viagens",
        "counterName": "mariagolcalves",
        "instagramUrl": "",
        "githubUrl": "https://github.com/mariagoncalves15",
        "projectUrl": "https://mariagoncalves15.github.io/Front-end-I/projeto_atualizado/",
        "imageSource": "default"
    },
    {
        "id": 1027,
        "type": "normal",
        "name": "Maria Fernanda",
        "projectName": "Blog CarePet",
        "projectCategory": "Natureza",
        "counterName": "mariafernanda",
        "instagramUrl": "",
        "githubUrl": "https://github.com/fernandaoooo",
        "projectUrl": "https://fernandaoooo.github.io/front-end-2/projetoMobile/",
        "imageSource": "default"
    },
    {
        "id": 1028,
        "type": "normal",
        "name": "Mariana Zorzi",
        "projectName": "Marvel",
        "projectCategory": "Filmes",
        "counterName": "marianazorzi",
        "instagramUrl": "",
        "githubUrl": "https://github.com/marianazorzi1",
        "projectUrl": "https://marianazorzi1.github.io/site/mobile/html/index.html",
        "imageSource": "default"
    },
    {
        "id": 1029,
        "type": "normal",
        "name": "Nathan Teixeira",
        "projectName": "Viagem do Gurismo",
        "projectCategory": "Viagens",
        "counterName": "nathanteixeira",
        "instagramUrl": "https://www.instagram.com/nathanteixeira55/",
        "githubUrl": "https://github.com/NathanTLopes",
        "projectUrl": "https://nathantlopes.github.io/Sites/Viagem%20do%20Gurismo/",
        "imageSource": "1029"
    },
    {
        "id": 1030,
        "type": "normal",
        "name": "Sofia Melo",
        "projectName": "Indicações de Livros",
        "projectCategory": "Livros",
        "counterName": "sofiamelo",
        "instagramUrl": "",
        "githubUrl": "https://github.com/melosofia",
        "projectUrl": "https://melosofia.github.io/PagInicial/projeto2/index.html",
        "imageSource": "default"
    },
    {
        "id": 1031,
        "type": "normal",
        "name": "Max Costa",
        "projectName": "GameArts",
        "projectCategory": "Tecnologia",
        "counterName": "maxcosta",
        "instagramUrl": "",
        "githubUrl": "https://github.com/maxcostacardosoifro",
        "projectUrl": "https://maxcostacardosoifro.github.io/site-sala-aula/index.html",
        "imageSource": "default"
    }
]